passguard_assistant/__init__.py
passguard_assistant/alerts.py
passguard_assistant/checker.py
passguard_assistant/cli.py
passguard_assistant/core.py
passguard_assistant/generator.py
passguard_assistant/hasher.py
passguard_assistant-0.3.2.dist-info/licenses/LICENSE
tests/test_basic.py
passguard_assistant-0.3.2.dist-info/METADATA
passguard_assistant-0.3.2.dist-info/WHEEL
passguard_assistant-0.3.2.dist-info/entry_points.txt
passguard_assistant-0.3.2.dist-info/top_level.txt
passguard_assistant-0.3.2.dist-info/RECORD
