Metadata-Version: 2.4
Name: passguard-assistant
Version: 0.3.2
Summary: Password health + hashing + security assistant: strength checks, smart suggestions, tokens, alerts.
Author: Sathish J
Author-email: Sathish J <jsathish587@gmail.com>
License-Expression: MIT
Project-URL: Homepage, https://github.com/sathishkevinmitnick
Project-URL: Bug Tracker, https://github.com/sathishkevinmitnick/passguard-assistant/issues
Keywords: password,security,entropy,strength,alert,email
Classifier: Programming Language :: Python :: 3
Classifier: Operating System :: OS Independent
Classifier: Topic :: Security :: Cryptography
Classifier: Intended Audience :: Developers
Requires-Python: >=3.10
License-File: LICENSE
Requires-Dist: argon2-cffi>=23.1.0
Requires-Dist: bcrypt>=4.0.1
Dynamic: author
Dynamic: license-file
Dynamic: requires-python
